__init__.py
__init__/__init__.py
__init__/example.py
turtlescrape_py/__init__.py
turtlescrape_py/example.py
turtlescrape-1.0.5.dist-info/LICENSE
turtlescrape-1.0.5.dist-info/METADATA
turtlescrape-1.0.5.dist-info/WHEEL
turtlescrape-1.0.5.dist-info/top_level.txt
turtlescrape-1.0.5.dist-info/RECORD
